AUTHORS
AUTHORS.md
COPYING
DEVELOPMENT
DEVELOPMENT.md
INSTALL
INSTALL.md
MANIFEST.in
README
README.md
README.rsync
README.rsync.md
TODO
TODO.md
setup.py
authprogs/__init__.py
authprogs/authprogs.py
authprogs/rsync.py
authprogs/scp.py
authprogs.egg-info/PKG-INFO
authprogs.egg-info/SOURCES.txt
authprogs.egg-info/dependency_links.txt
authprogs.egg-info/entry_points.txt
authprogs.egg-info/not-zip-safe
authprogs.egg-info/requires.txt
authprogs.egg-info/top_level.txt
doc/authprogs.1
doc/authprogs.html
doc/authprogs.md
doc/description.rst