Metadata-Version: 1.2
Name: authprogs
Version: 0.7.4
Summary: SSH Command Authenticator
Home-page: http://github.com/daethnir/authprogs
Author: Bri Hatch
Author-email: bri@ifokr.org
Maintainer: Bri Hatch
Maintainer-email: bri@ifokr.org
License: GPLv2
Keywords: authprogs ssh pubkey identity authorized_keys security
Platform: UNKNOWN
